aiohttp_boilerplate/__init__.py
aiohttp_boilerplate/auth/__init__.py
aiohttp_boilerplate/bootstrap/__init__.py
aiohttp_boilerplate/bootstrap/console_app.py
aiohttp_boilerplate/bootstrap/tests.py
aiohttp_boilerplate/bootstrap/web_app.py
aiohttp_boilerplate/config/__init__.py
aiohttp_boilerplate/dbpool/__init__.py
aiohttp_boilerplate/dbpool/dummy.py
aiohttp_boilerplate/dbpool/pg.py
aiohttp_boilerplate/dbpool/tests.py
aiohttp_boilerplate/logging/__init__.py
aiohttp_boilerplate/logging/formatter.py
aiohttp_boilerplate/logging/helpers.py
aiohttp_boilerplate/logging/logger.conf
aiohttp_boilerplate/middleware/__init__.py
aiohttp_boilerplate/middleware/defaults.py
aiohttp_boilerplate/models/__init__.py
aiohttp_boilerplate/schemas/__init__.py
aiohttp_boilerplate/schemas/fields.py
aiohttp_boilerplate/sql/__init__.py
aiohttp_boilerplate/sql/consts.py
aiohttp_boilerplate/sql/tests.py
aiohttp_boilerplate/test_utils/__init__.py
aiohttp_boilerplate/test_utils/e2e.py
aiohttp_boilerplate/test_utils/load_fixtures.py
aiohttp_boilerplate/test_utils/test_load_fixtures.py
aiohttp_boilerplate/test_utils/unit.py
aiohttp_boilerplate/views/__init__.py
aiohttp_boilerplate/views/create.py
aiohttp_boilerplate/views/exceptions.py
aiohttp_boilerplate/views/list.py
aiohttp_boilerplate/views/mixins.py
aiohttp_boilerplate/views/options.py
aiohttp_boilerplate/views/retrieve.py
aiohttp_boilerplate/views/update.py
aiohttp_boilerplate-0.2.6.dist-info/LICENSE
aiohttp_boilerplate-0.2.6.dist-info/WHEEL
aiohttp_boilerplate-0.2.6.dist-info/METADATA
aiohttp_boilerplate-0.2.6.dist-info/RECORD
